LICENSE.md
MANIFEST.in
README.md
pyproject.toml
setup.py
pytmt/__init__.py
pytmt/__main__.py
pytmt/correct_matrix.py
pytmt/get_spec.py
pytmt/logger.py
pytmt/main.py
pytmt/protein_group.py
pytmt/quantify_spec.py
pytmt/tmt_reporters.py
pytmt.egg-info/PKG-INFO
pytmt.egg-info/SOURCES.txt
pytmt.egg-info/dependency_links.txt
pytmt.egg-info/entry_points.txt
pytmt.egg-info/requires.txt
pytmt.egg-info/top_level.txt
tests/__init__.py
tests/test_tmt.py
tests/data/percolator/.DS_Store
tests/data/percolator/percolator.target.mzid
tests/data/percolator/percolator.target.psms.txt