Metadata-Version: 2.1
Name: pytmt
Version: 0.4.2
Summary: pytmt returns ms2 tmt quantification values from Crux Percolator output
Home-page: https://github.com/ed-lau/pytmt
Author: Edward Lau
Author-email: edward.lau@cuanschutz.edu
License: UNKNOWN
Project-URL: Source, https://github.com/ed-lau/pytmt
Project-URL: Lau Lab Colorado, https://laulab.net
Keywords: scientific proteomics mass-spectrometry
Platform: UNKNOWN
Classifier: Development Status :: 4 - Beta
Classifier: Intended Audience :: Developers
Classifier: Topic :: Software Development :: Build Tools
Classifier: License :: OSI Approved :: MIT License
Classifier: Programming Language :: Python :: 3.7
Classifier: Programming Language :: Python :: 3.8
Classifier: Programming Language :: Python :: 3.9
Classifier: Programming Language :: Python :: 3 :: Only
Requires-Python: >=3.6, <4
License-File: LICENSE.md
